inmanta_plugins/config/__init__.py
inmanta_plugins/config/abc.py
inmanta_plugins/config/const.py
inmanta_plugins/config/py.typed
inmanta_plugins/config/setup.cfg
inmanta_plugins/config/utils.py
inmanta_plugins/config/files/.gitkeep
inmanta_plugins/config/model/_init.cf
inmanta_plugins/config/templates/.gitkeep
inmanta_module_config-0.7.1.dist-info/METADATA
inmanta_module_config-0.7.1.dist-info/WHEEL
inmanta_module_config-0.7.1.dist-info/top_level.txt
inmanta_module_config-0.7.1.dist-info/RECORD
