Metadata-Version: 2.4
Name: inmanta-module-config
Version: 0.7.1
Author: Inmanta
Author-email: code@inmanta.com
License: Inmanta EULA
Requires-Dist: inmanta-module-std>=4.3.5
Requires-Dist: inmanta-core>=11.0.0
